Easy_Bot/__init__.py
Easy_Bot/_easyBot.py
Easy_Bot/_keyboard.py
Easy_Bot/_tasks.py
Easy_Bot/_functions/__function__.py
Easy_Bot/_functions/__init__.py
Easy_Bot/error/__init__.py
Easy_Bot/ext/__init__.py
Easy_Bot/ext/_client.py
Easy_Bot/ext/_commands.py
Easy_Bot/ext/_handlers.py
Easy_Bot/ext/_unauth.py
ptb_easy_bot-0.1.9.dist-info/LICENSE
ptb_easy_bot-0.1.9.dist-info/METADATA
ptb_easy_bot-0.1.9.dist-info/WHEEL
ptb_easy_bot-0.1.9.dist-info/top_level.txt
ptb_easy_bot-0.1.9.dist-info/RECORD
