Metadata-Version: 2.1
Name: ptb-easy-bot
Version: 0.1.9
Summary: A module for create python-telegram-bot with easy and fast
Author: Pamod Madubahana
Author-email: premiumqtrst@gmail.com
Keywords: python,telegram bot,Easy Bots
Classifier: Development Status :: 1 - Planning
Classifier: Intended Audience :: Developers
Classifier: Programming Language :: Python :: 3
Classifier: Operating System :: OS Independent
License-File: LICENSE
Requires-Dist: python-telegram-bot
Requires-Dist: python-telegram-bot[webhooks]
